README.rst
setup.py
simplebus_mail/__init__.py
simplebus_mail/config.py
simplebus_mail/exceptions.py
simplebus_mail/logging.py
simplebus_mail/mail.py
simplebus_mail/message.py
simplebus_mail.egg-info/PKG-INFO
simplebus_mail.egg-info/SOURCES.txt
simplebus_mail.egg-info/dependency_links.txt
simplebus_mail.egg-info/requires.txt
simplebus_mail.egg-info/top_level.txt