Metadata-Version: 1.1
Name: simplebus-mail
Version: 0.9.5
Summary: SimpleBus-Mail is a library for Python 3 which send emails using simplebus.
Home-page: https://github.com/viniciuschiele/simplebus-mail
Author: Vinicius Chiele
Author-email: vinicius.chiele@gmail.com
License: Apache 2.0
Keywords: simplebus,mail,email,smtp
Platform: UNKNOWN
Classifier: Development Status :: 5 - Production/Stable
Classifier: Intended Audience :: Developers
Classifier: Natural Language :: English
Classifier: Operating System :: OS Independent
Classifier: Programming Language :: Python :: 3
Classifier: Programming Language :: Python :: 3.2
Classifier: Programming Language :: Python :: 3.3
Classifier: Programming Language :: Python :: 3.4
Classifier: Programming Language :: Python :: Implementation :: CPython
Classifier: Topic :: Communications
Classifier: Topic :: Internet
Classifier: Topic :: Software Development :: Libraries
Classifier: Topic :: Software Development :: Libraries :: Python Modules
Classifier: Topic :: System :: Networking
